loafer/__init__.py
loafer/dispatchers.py
loafer/exceptions.py
loafer/managers.py
loafer/message_translators.py
loafer/providers.py
loafer/routes.py
loafer/runners.py
loafer/utils.py
loafer/ext/__init__.py
loafer/ext/sentry.py
loafer/ext/aws/__init__.py
loafer/ext/aws/bases.py
loafer/ext/aws/handlers.py
loafer/ext/aws/message_translators.py
loafer/ext/aws/providers.py
loafer/ext/aws/routes.py
loafer-2.0.1.dist-info/LICENSE
loafer-2.0.1.dist-info/METADATA
loafer-2.0.1.dist-info/WHEEL
loafer-2.0.1.dist-info/top_level.txt
loafer-2.0.1.dist-info/RECORD
