Metadata-Version: 2.1
Name: loafer
Version: 2.0.1
Summary: Asynchronous message dispatcher for concurrent tasks processing
Home-page: https://github.com/georgeyk/loafer/
Author: George Y. Kussumoto
Author-email: contato@georgeyk.com.br
License: MIT
Download-URL: https://github.com/georgeyk/loafer/releases
Keywords: asynchronous asyncio message dispatcher tasks microservices
Platform: UNKNOWN
Classifier: Development Status :: 4 - Beta
Classifier: Environment :: Console
Classifier: Intended Audience :: Developers
Classifier: License :: OSI Approved :: MIT License
Classifier: Natural Language :: English
Classifier: Operating System :: OS Independent
Classifier: Programming Language :: Python :: 3.6
Classifier: Programming Language :: Python :: 3.7
Classifier: Programming Language :: Python :: 3.8
Classifier: Topic :: System :: Distributed Computing
Requires-Python: >=3.6
Requires-Dist: aiobotocore[boto3] (<2,>=1.0.4)
Requires-Dist: cached-property (<2,>=1.3.0)
